trac2markdown/__init__.py
trac2markdown/format_wikis.py
trac2markdown/format_wikis_config.py.sample
trac2markdown/version.py
trac2markdown-1.0.0.dist-info/METADATA
trac2markdown-1.0.0.dist-info/WHEEL
trac2markdown-1.0.0.dist-info/licenses/LICENSE
trac2markdown-1.0.0.dist-info/RECORD
