Metadata-Version: 2.3
Name: trac2markdown
Version: 1.0.0
Summary: Open-source Python package for formatting text from Trac's Markdown syntax to the standard Markdown format.
Project-URL: Homepage, https://github.com/veselatrajkoska/trac_to_markdown
Project-URL: Documentation, https://trac-to-markdown.readthedocs.io/en/latest/
Project-URL: Issues, https://github.com/veselatrajkoska/trac_to_markdown/issues
Author-email: Vesela Trajkoska <veselatrajkoska2@gmail.com>
License-File: LICENSE
Classifier: License :: OSI Approved :: GNU General Public License v3 (GPLv3)
Classifier: Operating System :: OS Independent
Classifier: Programming Language :: Python :: 3
Requires-Python: >=3.8
